{"/":{"title":"Introduction","data":{"":"","hello-world#Hello World!":"This will soon be something......"}},"/blog/2023-02-07--Hello-World":{"title":"Hello World","data":{"":"This is a test."}},"/another":{"title":"Another Page","data":{"":"let a = 1;\n\nconsole.log(a);","component#Component":"","external-component#External Component":""}},"/advanced":{"title":"Advanced","data":{"":"This is the index page for the Advanced folder!"}},"/advanced/satori":{"title":"Satori","data":{"":"Satori (悟り) is a Japanese Buddhist term for awakening, \"comprehension; understanding\"."}},"/blog":{"title":"Weblog","data":{"":"","hello-world#Hello World!":"This will soon be home to my second brain, docs, etc."}},"/blog/2023-02-07--Hello-World2":{"title":"Hello World 2","data":{"":"Another page."}},"/about":{"title":"About","data":{"":"This is the about page! This page is shown on the navbar."}}}